[
    {
        "buffer_voltage_mv": 1200.0,
        "efficiency": -0.023,
        "frequency_mhz": 868.0,
        "level_dbm": -13.965,
        "pwr_pw": -9396.0,
        "resistance": 0.0,
        "source": "datasheet",
        "target_voltage_mv": 0.0,
        "tuning_frequency_mhz": 915.0
    },
    {
        "buffer_voltage_mv": 1200.0,
        "efficiency": 0.342,
        "frequency_mhz": 868.0,
        "level_dbm": -11.558,
        "pwr_pw": 239064.0,
        "resistance": 0.0,
        "source": "datasheet",
        "target_voltage_mv": 0.0,
        "tuning_frequency_mhz": 915.0
    },
    {
        "buffer_voltage_mv": 1200.0,
        "efficiency": 0.699,
        "frequency_mhz": 868.0,
        "level_dbm": -11.027,
        "pwr_pw": 551514.0,
        "resistance": 0.0,
        "source": "datasheet",
        "target_voltage_mv": 0.0,
        "tuning_frequency_mhz": 915.0
    },
    {
        "buffer_voltage_mv": 1200.0,
        "efficiency": 9.43,
        "frequency_mhz": 868.0,
        "level_dbm": -9.965,
        "pwr_pw": 9507383.0,
        "resistance": 0.0,
        "source": "datasheet",
        "target_voltage_mv": 0.0,
        "tuning_frequency_mhz": 915.0
    },
    {
        "buffer_voltage_mv": 1200.0,
        "efficiency": 22.76,
        "frequency_mhz": 868.0,
        "level_dbm": -9.009,
        "pwr_pw": 28595285.0,
        "resistance": 0.0,
        "source": "datasheet",
        "target_voltage_mv": 0.0,
        "tuning_frequency_mhz": 915.0
    },
    {
        "buffer_voltage_mv": 1200.0,
        "efficiency": 35.029,
        "frequency_mhz": 868.0,
        "level_dbm": -8.018,
        "pwr_pw": 55292053.0,
        "resistance": 0.0,
        "source": "datasheet",
        "target_voltage_mv": 0.0,
        "tuning_frequency_mhz": 915.0
    },
    {
        "buffer_voltage_mv": 1200.0,
        "efficiency": 43.761,
        "frequency_mhz": 868.0,
        "level_dbm": -7.027,
        "pwr_pw": 86781907.0,
        "resistance": 0.0,
        "source": "datasheet",
        "target_voltage_mv": 0.0,
        "tuning_frequency_mhz": 915.0
    },
    {
        "buffer_voltage_mv": 1200.0,
        "efficiency": 49.426,
        "frequency_mhz": 868.0,
        "level_dbm": -6.0,
        "pwr_pw": 124152752.0,
        "resistance": 0.0,
        "source": "datasheet",
        "target_voltage_mv": 0.0,
        "tuning_frequency_mhz": 915.0
    },
    {
        "buffer_voltage_mv": 1200.0,
        "efficiency": 52.497,
        "frequency_mhz": 868.0,
        "level_dbm": -4.973,
        "pwr_pw": 167028608.0,
        "resistance": 0.0,
        "source": "datasheet",
        "target_voltage_mv": 0.0,
        "tuning_frequency_mhz": 915.0
    },
    {
        "buffer_voltage_mv": 1200.0,
        "efficiency": 53.092,
        "frequency_mhz": 868.0,
        "level_dbm": -3.982,
        "pwr_pw": 212224901.0,
        "resistance": 0.0,
        "source": "datasheet",
        "target_voltage_mv": 0.0,
        "tuning_frequency_mhz": 915.0
    },
    {
        "buffer_voltage_mv": 1200.0,
        "efficiency": 52.743,
        "frequency_mhz": 868.0,
        "level_dbm": -3.027,
        "pwr_pw": 262728174.0,
        "resistance": 0.0,
        "source": "datasheet",
        "target_voltage_mv": 0.0,
        "tuning_frequency_mhz": 915.0
    },
    {
        "buffer_voltage_mv": 1200.0,
        "efficiency": 51.333,
        "frequency_mhz": 868.0,
        "level_dbm": -2.0,
        "pwr_pw": 323886476.0,
        "resistance": 0.0,
        "source": "datasheet",
        "target_voltage_mv": 0.0,
        "tuning_frequency_mhz": 915.0
    },
    {
        "buffer_voltage_mv": 1200.0,
        "efficiency": 50.63,
        "frequency_mhz": 868.0,
        "level_dbm": -0.938,
        "pwr_pw": 407947698.0,
        "resistance": 0.0,
        "source": "datasheet",
        "target_voltage_mv": 0.0,
        "tuning_frequency_mhz": 915.0
    },
    {
        "buffer_voltage_mv": 1200.0,
        "efficiency": 56.654,
        "frequency_mhz": 868.0,
        "level_dbm": 0.973,
        "pwr_pw": 708881887.0,
        "resistance": 0.0,
        "source": "datasheet",
        "target_voltage_mv": 0.0,
        "tuning_frequency_mhz": 915.0
    },
    {
        "buffer_voltage_mv": 1200.0,
        "efficiency": 59.253,
        "frequency_mhz": 868.0,
        "level_dbm": 1.965,
        "pwr_pw": 931473076.0,
        "resistance": 0.0,
        "source": "datasheet",
        "target_voltage_mv": 0.0,
        "tuning_frequency_mhz": 915.0
    },
    {
        "buffer_voltage_mv": 1200.0,
        "efficiency": 60.909,
        "frequency_mhz": 868.0,
        "level_dbm": 2.991,
        "pwr_pw": 1212819622.0,
        "resistance": 0.0,
        "source": "datasheet",
        "target_voltage_mv": 0.0,
        "tuning_frequency_mhz": 915.0
    },
    {
        "buffer_voltage_mv": 1200.0,
        "efficiency": 61.857,
        "frequency_mhz": 868.0,
        "level_dbm": 4.018,
        "pwr_pw": 1560132777.0,
        "resistance": 0.0,
        "source": "datasheet",
        "target_voltage_mv": 0.0,
        "tuning_frequency_mhz": 915.0
    },
    {
        "buffer_voltage_mv": 1200.0,
        "efficiency": 61.744,
        "frequency_mhz": 868.0,
        "level_dbm": 5.009,
        "pwr_pw": 1956510285.0,
        "resistance": 0.0,
        "source": "datasheet",
        "target_voltage_mv": 0.0,
        "tuning_frequency_mhz": 915.0
    },
    {
        "buffer_voltage_mv": 1200.0,
        "efficiency": 61.041,
        "frequency_mhz": 868.0,
        "level_dbm": 5.965,
        "pwr_pw": 2410378931.0,
        "resistance": 0.0,
        "source": "datasheet",
        "target_voltage_mv": 0.0,
        "tuning_frequency_mhz": 915.0
    },
    {
        "buffer_voltage_mv": 1200.0,
        "efficiency": 59.396,
        "frequency_mhz": 868.0,
        "level_dbm": 6.991,
        "pwr_pw": 2970771639.0,
        "resistance": 0.0,
        "source": "datasheet",
        "target_voltage_mv": 0.0,
        "tuning_frequency_mhz": 915.0
    },
    {
        "buffer_voltage_mv": 1200.0,
        "efficiency": 57.16,
        "frequency_mhz": 868.0,
        "level_dbm": 8.018,
        "pwr_pw": 3621284726.0,
        "resistance": 0.0,
        "source": "datasheet",
        "target_voltage_mv": 0.0,
        "tuning_frequency_mhz": 915.0
    },
    {
        "buffer_voltage_mv": 1200.0,
        "efficiency": 54.571,
        "frequency_mhz": 868.0,
        "level_dbm": 9.009,
        "pwr_pw": 4343538725.0,
        "resistance": 0.0,
        "source": "datasheet",
        "target_voltage_mv": 0.0,
        "tuning_frequency_mhz": 915.0
    },
    {
        "buffer_voltage_mv": 1200.0,
        "efficiency": 51.51,
        "frequency_mhz": 868.0,
        "level_dbm": 10.035,
        "pwr_pw": 5193116517.0,
        "resistance": 0.0,
        "source": "datasheet",
        "target_voltage_mv": 0.0,
        "tuning_frequency_mhz": 915.0
    },
    {
        "buffer_voltage_mv": 1200.0,
        "efficiency": 48.33,
        "frequency_mhz": 868.0,
        "level_dbm": 10.991,
        "pwr_pw": 6072044004.0,
        "resistance": 0.0,
        "source": "datasheet",
        "target_voltage_mv": 0.0,
        "tuning_frequency_mhz": 915.0
    },
    {
        "buffer_voltage_mv": 1200.0,
        "efficiency": 0.213,
        "frequency_mhz": 915.0,
        "level_dbm": -13.894,
        "pwr_pw": 86809.0,
        "resistance": 0.0,
        "source": "datasheet",
        "target_voltage_mv": 0.0,
        "tuning_frequency_mhz": 915.0
    },
    {
        "buffer_voltage_mv": 1200.0,
        "efficiency": 1.986,
        "frequency_mhz": 915.0,
        "level_dbm": -13.044,
        "pwr_pw": 985183.0,
        "resistance": 0.0,
        "source": "datasheet",
        "target_voltage_mv": 0.0,
        "tuning_frequency_mhz": 915.0
    },
    {
        "buffer_voltage_mv": 1200.0,
        "efficiency": 8.123,
        "frequency_mhz": 915.0,
        "level_dbm": -11.982,
        "pwr_pw": 5146274.0,
        "resistance": 0.0,
        "source": "datasheet",
        "target_voltage_mv": 0.0,
        "tuning_frequency_mhz": 915.0
    },
    {
        "buffer_voltage_mv": 1200.0,
        "efficiency": 21.453,
        "frequency_mhz": 915.0,
        "level_dbm": -11.027,
        "pwr_pw": 16937099.0,
        "resistance": 0.0,
        "source": "datasheet",
        "target_voltage_mv": 0.0,
        "tuning_frequency_mhz": 915.0
    },
    {
        "buffer_voltage_mv": 1200.0,
        "efficiency": 34.784,
        "frequency_mhz": 915.0,
        "level_dbm": -10.0,
        "pwr_pw": 34783805.0,
        "resistance": 0.0,
        "source": "datasheet",
        "target_voltage_mv": 0.0,
        "tuning_frequency_mhz": 915.0
    },
    {
        "buffer_voltage_mv": 1200.0,
        "efficiency": 43.869,
        "frequency_mhz": 915.0,
        "level_dbm": -9.009,
        "pwr_pw": 55115205.0,
        "resistance": 0.0,
        "source": "datasheet",
        "target_voltage_mv": 0.0,
        "tuning_frequency_mhz": 915.0
    },
    {
        "buffer_voltage_mv": 1200.0,
        "efficiency": 50.006,
        "frequency_mhz": 915.0,
        "level_dbm": -8.018,
        "pwr_pw": 78931535.0,
        "resistance": 0.0,
        "source": "datasheet",
        "target_voltage_mv": 0.0,
        "tuning_frequency_mhz": 915.0
    },
    {
        "buffer_voltage_mv": 1200.0,
        "efficiency": 53.43,
        "frequency_mhz": 915.0,
        "level_dbm": -7.027,
        "pwr_pw": 105958132.0,
        "resistance": 0.0,
        "source": "datasheet",
        "target_voltage_mv": 0.0,
        "tuning_frequency_mhz": 915.0
    },
    {
        "buffer_voltage_mv": 1200.0,
        "efficiency": 55.086,
        "frequency_mhz": 915.0,
        "level_dbm": -6.035,
        "pwr_pw": 137247301.0,
        "resistance": 0.0,
        "source": "datasheet",
        "target_voltage_mv": 0.0,
        "tuning_frequency_mhz": 915.0
    },
    {
        "buffer_voltage_mv": 1200.0,
        "efficiency": 54.855,
        "frequency_mhz": 915.0,
        "level_dbm": -5.009,
        "pwr_pw": 173115205.0,
        "resistance": 0.0,
        "source": "datasheet",
        "target_voltage_mv": 0.0,
        "tuning_frequency_mhz": 915.0
    },
    {
        "buffer_voltage_mv": 1200.0,
        "efficiency": 53.563,
        "frequency_mhz": 915.0,
        "level_dbm": -4.018,
        "pwr_pw": 212371677.0,
        "resistance": 0.0,
        "source": "datasheet",
        "target_voltage_mv": 0.0,
        "tuning_frequency_mhz": 915.0
    },
    {
        "buffer_voltage_mv": 1200.0,
        "efficiency": 51.917,
        "frequency_mhz": 915.0,
        "level_dbm": -2.991,
        "pwr_pw": 260733631.0,
        "resistance": 0.0,
        "source": "datasheet",
        "target_voltage_mv": 0.0,
        "tuning_frequency_mhz": 915.0
    },
    {
        "buffer_voltage_mv": 1200.0,
        "efficiency": 52.866,
        "frequency_mhz": 915.0,
        "level_dbm": -2.0,
        "pwr_pw": 333559172.0,
        "resistance": 0.0,
        "source": "datasheet",
        "target_voltage_mv": 0.0,
        "tuning_frequency_mhz": 915.0
    },
    {
        "buffer_voltage_mv": 1200.0,
        "efficiency": 56.88,
        "frequency_mhz": 915.0,
        "level_dbm": -0.973,
        "pwr_pw": 454584675.0,
        "resistance": 0.0,
        "source": "datasheet",
        "target_voltage_mv": 0.0,
        "tuning_frequency_mhz": 915.0
    },
    {
        "buffer_voltage_mv": 1200.0,
        "efficiency": 59.361,
        "frequency_mhz": 915.0,
        "level_dbm": -0.018,
        "pwr_pw": 591197287.0,
        "resistance": 0.0,
        "source": "datasheet",
        "target_voltage_mv": 0.0,
        "tuning_frequency_mhz": 915.0
    },
    {
        "buffer_voltage_mv": 1200.0,
        "efficiency": 61.253,
        "frequency_mhz": 915.0,
        "level_dbm": 0.973,
        "pwr_pw": 766427720.0,
        "resistance": 0.0,
        "source": "datasheet",
        "target_voltage_mv": 0.0,
        "tuning_frequency_mhz": 915.0
    },
    {
        "buffer_voltage_mv": 1200.0,
        "efficiency": 62.319,
        "frequency_mhz": 915.0,
        "level_dbm": 2.0,
        "pwr_pw": 987692479.0,
        "resistance": 0.0,
        "source": "datasheet",
        "target_voltage_mv": 0.0,
        "tuning_frequency_mhz": 915.0
    },
    {
        "buffer_voltage_mv": 1200.0,
        "efficiency": 62.678,
        "frequency_mhz": 915.0,
        "level_dbm": 2.991,
        "pwr_pw": 1248041333.0,
        "resistance": 0.0,
        "source": "datasheet",
        "target_voltage_mv": 0.0,
        "tuning_frequency_mhz": 915.0
    },
    {
        "buffer_voltage_mv": 1200.0,
        "efficiency": 62.211,
        "frequency_mhz": 915.0,
        "level_dbm": 3.982,
        "pwr_pw": 1556314116.0,
        "resistance": 0.0,
        "source": "datasheet",
        "target_voltage_mv": 0.0,
        "tuning_frequency_mhz": 915.0
    },
    {
        "buffer_voltage_mv": 1200.0,
        "efficiency": 60.919,
        "frequency_mhz": 915.0,
        "level_dbm": 4.973,
        "pwr_pw": 1914677998.0,
        "resistance": 0.0,
        "source": "datasheet",
        "target_voltage_mv": 0.0,
        "tuning_frequency_mhz": 915.0
    },
    {
        "buffer_voltage_mv": 1200.0,
        "efficiency": 59.155,
        "frequency_mhz": 915.0,
        "level_dbm": 6.0,
        "pwr_pw": 2354997960.0,
        "resistance": 0.0,
        "source": "datasheet",
        "target_voltage_mv": 0.0,
        "tuning_frequency_mhz": 915.0
    },
    {
        "buffer_voltage_mv": 1200.0,
        "efficiency": 56.919,
        "frequency_mhz": 915.0,
        "level_dbm": 6.991,
        "pwr_pw": 2846909525.0,
        "resistance": 0.0,
        "source": "datasheet",
        "target_voltage_mv": 0.0,
        "tuning_frequency_mhz": 915.0
    },
    {
        "buffer_voltage_mv": 1200.0,
        "efficiency": 54.212,
        "frequency_mhz": 915.0,
        "level_dbm": 8.018,
        "pwr_pw": 3434511738.0,
        "resistance": 0.0,
        "source": "datasheet",
        "target_voltage_mv": 0.0,
        "tuning_frequency_mhz": 915.0
    },
    {
        "buffer_voltage_mv": 1200.0,
        "efficiency": 51.387,
        "frequency_mhz": 915.0,
        "level_dbm": 9.009,
        "pwr_pw": 4090111733.0,
        "resistance": 0.0,
        "source": "datasheet",
        "target_voltage_mv": 0.0,
        "tuning_frequency_mhz": 915.0
    },
    {
        "buffer_voltage_mv": 1200.0,
        "efficiency": 48.09,
        "frequency_mhz": 915.0,
        "level_dbm": 10.035,
        "pwr_pw": 4848336594.0,
        "resistance": 0.0,
        "source": "datasheet",
        "target_voltage_mv": 0.0,
        "tuning_frequency_mhz": 915.0
    },
    {
        "buffer_voltage_mv": 1200.0,
        "efficiency": 44.911,
        "frequency_mhz": 915.0,
        "level_dbm": 11.027,
        "pwr_pw": 5688591310.0,
        "resistance": 0.0,
        "source": "datasheet",
        "target_voltage_mv": 0.0,
        "tuning_frequency_mhz": 915.0
    },
    {
        "buffer_voltage_mv": 1200.0,
        "efficiency": -0.023,
        "frequency_mhz": 950.0,
        "level_dbm": -13.929,
        "pwr_pw": -9403.0,
        "resistance": 0.0,
        "source": "datasheet",
        "target_voltage_mv": 0.0,
        "tuning_frequency_mhz": 915.0
    },
    {
        "buffer_voltage_mv": 1200.0,
        "efficiency": 0.099,
        "frequency_mhz": 950.0,
        "level_dbm": -12.973,
        "pwr_pw": 50115.0,
        "resistance": 0.0,
        "source": "datasheet",
        "target_voltage_mv": 0.0,
        "tuning_frequency_mhz": 915.0
    },
    {
        "buffer_voltage_mv": 1200.0,
        "efficiency": 3.288,
        "frequency_mhz": 950.0,
        "level_dbm": -12.018,
        "pwr_pw": 2066177.0,
        "resistance": 0.0,
        "source": "datasheet",
        "target_voltage_mv": 0.0,
        "tuning_frequency_mhz": 915.0
    },
    {
        "buffer_voltage_mv": 1200.0,
        "efficiency": 13.199,
        "frequency_mhz": 950.0,
        "level_dbm": -11.027,
        "pwr_pw": 10420105.0,
        "resistance": 0.0,
        "source": "datasheet",
        "target_voltage_mv": 0.0,
        "tuning_frequency_mhz": 915.0
    },
    {
        "buffer_voltage_mv": 1200.0,
        "efficiency": 26.765,
        "frequency_mhz": 950.0,
        "level_dbm": -10.0,
        "pwr_pw": 26764937.0,
        "resistance": 0.0,
        "source": "datasheet",
        "target_voltage_mv": 0.0,
        "tuning_frequency_mhz": 915.0
    },
    {
        "buffer_voltage_mv": 1200.0,
        "efficiency": 36.675,
        "frequency_mhz": 950.0,
        "level_dbm": -9.009,
        "pwr_pw": 46077690.0,
        "resistance": 0.0,
        "source": "datasheet",
        "target_voltage_mv": 0.0,
        "tuning_frequency_mhz": 915.0
    },
    {
        "buffer_voltage_mv": 1200.0,
        "efficiency": 43.284,
        "frequency_mhz": 950.0,
        "level_dbm": -8.018,
        "pwr_pw": 68321689.0,
        "resistance": 0.0,
        "source": "datasheet",
        "target_voltage_mv": 0.0,
        "tuning_frequency_mhz": 915.0
    },
    {
        "buffer_voltage_mv": 1200.0,
        "efficiency": 47.652,
        "frequency_mhz": 950.0,
        "level_dbm": -6.991,
        "pwr_pw": 95272902.0,
        "resistance": 0.0,
        "source": "datasheet",
        "target_voltage_mv": 0.0,
        "tuning_frequency_mhz": 915.0
    },
    {
        "buffer_voltage_mv": 1200.0,
        "efficiency": 49.662,
        "frequency_mhz": 950.0,
        "level_dbm": -6.0,
        "pwr_pw": 124745178.0,
        "resistance": 0.0,
        "source": "datasheet",
        "target_voltage_mv": 0.0,
        "tuning_frequency_mhz": 915.0
    },
    {
        "buffer_voltage_mv": 1200.0,
        "efficiency": 50.021,
        "frequency_mhz": 950.0,
        "level_dbm": -5.009,
        "pwr_pw": 157857014.0,
        "resistance": 0.0,
        "source": "datasheet",
        "target_voltage_mv": 0.0,
        "tuning_frequency_mhz": 915.0
    },
    {
        "buffer_voltage_mv": 1200.0,
        "efficiency": 50.497,
        "frequency_mhz": 950.0,
        "level_dbm": -4.018,
        "pwr_pw": 200215204.0,
        "resistance": 0.0,
        "source": "datasheet",
        "target_voltage_mv": 0.0,
        "tuning_frequency_mhz": 915.0
    },
    {
        "buffer_voltage_mv": 1200.0,
        "efficiency": 53.332,
        "frequency_mhz": 950.0,
        "level_dbm": -3.027,
        "pwr_pw": 265665278.0,
        "resistance": 0.0,
        "source": "datasheet",
        "target_voltage_mv": 0.0,
        "tuning_frequency_mhz": 915.0
    },
    {
        "buffer_voltage_mv": 1200.0,
        "efficiency": 56.875,
        "frequency_mhz": 950.0,
        "level_dbm": -2.0,
        "pwr_pw": 358856990.0,
        "resistance": 0.0,
        "source": "datasheet",
        "target_voltage_mv": 0.0,
        "tuning_frequency_mhz": 915.0
    },
    {
        "buffer_voltage_mv": 1200.0,
        "efficiency": 59.474,
        "frequency_mhz": 950.0,
        "level_dbm": -1.009,
        "pwr_pw": 471458775.0,
        "resistance": 0.0,
        "source": "datasheet",
        "target_voltage_mv": 0.0,
        "tuning_frequency_mhz": 915.0
    },
    {
        "buffer_voltage_mv": 1200.0,
        "efficiency": 60.776,
        "frequency_mhz": 950.0,
        "level_dbm": 0.018,
        "pwr_pw": 610246154.0,
        "resistance": 0.0,
        "source": "datasheet",
        "target_voltage_mv": 0.0,
        "tuning_frequency_mhz": 915.0
    },
    {
        "buffer_voltage_mv": 1200.0,
        "efficiency": 61.371,
        "frequency_mhz": 950.0,
        "level_dbm": 1.009,
        "pwr_pw": 774190008.0,
        "resistance": 0.0,
        "source": "datasheet",
        "target_voltage_mv": 0.0,
        "tuning_frequency_mhz": 915.0
    },
    {
        "buffer_voltage_mv": 1200.0,
        "efficiency": 61.381,
        "frequency_mhz": 950.0,
        "level_dbm": 2.991,
        "pwr_pw": 1222212078.0,
        "resistance": 0.0,
        "source": "datasheet",
        "target_voltage_mv": 0.0,
        "tuning_frequency_mhz": 915.0
    },
    {
        "buffer_voltage_mv": 1200.0,
        "efficiency": 60.796,
        "frequency_mhz": 950.0,
        "level_dbm": 3.982,
        "pwr_pw": 1520913120.0,
        "resistance": 0.0,
        "source": "datasheet",
        "target_voltage_mv": 0.0,
        "tuning_frequency_mhz": 915.0
    },
    {
        "buffer_voltage_mv": 1200.0,
        "efficiency": 59.386,
        "frequency_mhz": 950.0,
        "level_dbm": 4.973,
        "pwr_pw": 1866495131.0,
        "resistance": 0.0,
        "source": "datasheet",
        "target_voltage_mv": 0.0,
        "tuning_frequency_mhz": 915.0
    },
    {
        "buffer_voltage_mv": 1200.0,
        "efficiency": 57.504,
        "frequency_mhz": 950.0,
        "level_dbm": 6.0,
        "pwr_pw": 2289272719.0,
        "resistance": 0.0,
        "source": "datasheet",
        "target_voltage_mv": 0.0,
        "tuning_frequency_mhz": 915.0
    },
    {
        "buffer_voltage_mv": 1200.0,
        "efficiency": 55.15,
        "frequency_mhz": 950.0,
        "level_dbm": 6.991,
        "pwr_pw": 2758436587.0,
        "resistance": 0.0,
        "source": "datasheet",
        "target_voltage_mv": 0.0,
        "tuning_frequency_mhz": 915.0
    },
    {
        "buffer_voltage_mv": 1200.0,
        "efficiency": 49.618,
        "frequency_mhz": 950.0,
        "level_dbm": 9.009,
        "pwr_pw": 3949318960.0,
        "resistance": 0.0,
        "source": "datasheet",
        "target_voltage_mv": 0.0,
        "tuning_frequency_mhz": 915.0
    },
    {
        "buffer_voltage_mv": 1200.0,
        "efficiency": 47.028,
        "frequency_mhz": 950.0,
        "level_dbm": 10.0,
        "pwr_pw": 4702830189.0,
        "resistance": 0.0,
        "source": "datasheet",
        "target_voltage_mv": 0.0,
        "tuning_frequency_mhz": 915.0
    },
    {
        "buffer_voltage_mv": 1200.0,
        "efficiency": 43.967,
        "frequency_mhz": 950.0,
        "level_dbm": 11.027,
        "pwr_pw": 5569096511.0,
        "resistance": 0.0,
        "source": "datasheet",
        "target_voltage_mv": 0.0,
        "tuning_frequency_mhz": 915.0
    }
]